capital/__init__.py
capital/_util/__init__.py
capital/_util/capitaldata.py
capital/dataset/__init__.py
capital/dataset/dataset.py
capital/pl/__init__.py
capital/pl/pl.py
capital/tl/__init__.py
capital/tl/_dynamic_time_warping.py
capital/tl/_preprocess.py
capital/tl/_tree_alignment.py
capital/tl/tl.py
capital-1.0.12.dist-info/LICENSE.txt
capital-1.0.12.dist-info/METADATA
capital-1.0.12.dist-info/WHEEL
capital-1.0.12.dist-info/top_level.txt
capital-1.0.12.dist-info/RECORD
