Metadata-Version: 2.1
Name: capital
Version: 1.0.12
Summary: Single-Cell Analysis, comparing pseudotime trajectories                 with tree alignment
Home-page: https://github.com/ykat0/capital
Author: Reiichi Sugihara, Yuki Kato, Tomoya Mori, Yukio Kawahara
Author-email: reiichi.sugihara@gmail.com
License: BSD-3-Clause
Classifier: Development Status :: 5 - Production/Stable
Classifier: License :: OSI Approved :: BSD License
Classifier: Framework :: Jupyter
Classifier: Intended Audience :: Developers
Classifier: Intended Audience :: Science/Research
Classifier: Natural Language :: English
Classifier: Programming Language :: Python
Classifier: Programming Language :: Python :: 3
Classifier: Programming Language :: Python :: 3.8
Classifier: Topic :: Scientific/Engineering :: Bio-Informatics
Classifier: Topic :: Scientific/Engineering :: Visualization
License-File: LICENSE.txt
Requires-Dist: anndata (>=0.7.4)
Requires-Dist: graphtools
Requires-Dist: graphviz
Requires-Dist: h5py (>=2.10.0)
Requires-Dist: leidenalg
Requires-Dist: magic-impute
Requires-Dist: matplotlib (>=3.1.2)
Requires-Dist: networkx (<=2.8.2)
Requires-Dist: numpy (>=1.17.0)
Requires-Dist: pandas (>=0.21)
Requires-Dist: pydot
Requires-Dist: scanpy (==1.9.1)
Requires-Dist: scikit-learn
Requires-Dist: scipy (>=1.4)
Requires-Dist: scprep
Requires-Dist: tslearn
